Metadata-Version: 2.2
Name: idiomatch
Version: 0.2.14
Summary: Spacy's Matcher specifically designed for matching English idioms
Requires-Python: <=3.12,>=3.10
Requires-Dist: spacy>=3.8.4
Requires-Dist: loguru>=0.7.3
Requires-Dist: pyyaml>=6.0.2
Requires-Dist: pydantic>=2.10.6
